pgsync/__init__.py
pgsync/base.py
pgsync/constants.py
pgsync/exc.py
pgsync/helper.py
pgsync/node.py
pgsync/plugin.py
pgsync/querybuilder.py
pgsync/redisqueue.py
pgsync/search_client.py
pgsync/settings.py
pgsync/singleton.py
pgsync/sync.py
pgsync/transform.py
pgsync/trigger.py
pgsync/urls.py
pgsync/utils.py
pgsync/view.py
pgsync_fork-2.7.3.data/scripts/bootstrap
pgsync_fork-2.7.3.data/scripts/parallel_sync
pgsync_fork-2.7.3.data/scripts/pgsync
pgsync_fork-2.7.3.dist-info/AUTHORS.rst
pgsync_fork-2.7.3.dist-info/LICENSE
pgsync_fork-2.7.3.dist-info/METADATA
pgsync_fork-2.7.3.dist-info/WHEEL
pgsync_fork-2.7.3.dist-info/top_level.txt
pgsync_fork-2.7.3.dist-info/RECORD
