Metadata-Version: 2.1
Name: pgsync-fork
Version: 2.7.3
Summary: Postgres to Elasticsearch/OpenSearch sync
Home-page: https://github.com/toluaina/pgsync
Author: Tolu Aina
Author-email: tolu@pgsync.com
Maintainer: Tolu Aina
Maintainer-email: tolu@pgsync.com
License: LGPLv3
Project-URL: Bug Reports, https://github.com/toluaina/pgsync/issues
Project-URL: Funding, https://github.com/sponsors/toluaina
Project-URL: Source, https://github.com/toluaina/pgsync
Project-URL: Web, https://pgsync.com
Project-URL: Documentation, https://pgsync.com
Keywords: pgsync,elasticsearch,opensearch,postgres,change data capture
Classifier: Development Status :: 5 - Production/Stable
Classifier: Intended Audience :: Developers
Classifier: Natural Language :: English
Classifier: Programming Language :: Python :: 3.7
Classifier: Programming Language :: Python :: 3.8
Classifier: Programming Language :: Python :: 3.9
Classifier: Programming Language :: Python :: 3.10
Classifier: Programming Language :: Python :: 3.11
Classifier: Programming Language :: Python :: Implementation :: CPython
Classifier: Programming Language :: Python :: Implementation :: PyPy
Classifier: License :: OSI Approved :: GNU Lesser General Public License v3 (LGPLv3)
Requires-Python: >=3.7.0
License-File: LICENSE
License-File: AUTHORS.rst
Requires-Dist: async-timeout (==4.0.2)
Requires-Dist: black (==23.7.0)
Requires-Dist: boto3 (==1.28.8)
Requires-Dist: botocore (==1.31.8)
Requires-Dist: certifi (==2023.5.7)
Requires-Dist: charset-normalizer (==3.2.0)
Requires-Dist: click (==8.1.6)
Requires-Dist: elasticsearch (==7.13.4)
Requires-Dist: elasticsearch-dsl (==7.4.1)
Requires-Dist: environs (==9.5.0)
Requires-Dist: faker (==19.2.0)
Requires-Dist: greenlet (==2.0.2)
Requires-Dist: idna (==3.4)
Requires-Dist: isort (==5.11.5)
Requires-Dist: jmespath (==1.0.1)
Requires-Dist: marshmallow (==3.20.1)
Requires-Dist: mypy-extensions (==1.0.0)
Requires-Dist: opensearch-dsl (==2.1.0)
Requires-Dist: opensearch-py (==2.2.0)
Requires-Dist: packaging (==23.1)
Requires-Dist: pathspec (==0.11.1)
Requires-Dist: platformdirs (==3.9.1)
Requires-Dist: psycopg2-binary (==2.9.6)
Requires-Dist: python-dateutil (==2.8.2)
Requires-Dist: python-dotenv (==0.21.1)
Requires-Dist: redis (==4.6.0)
Requires-Dist: requests (==2.31.0)
Requires-Dist: requests-aws4auth (==1.2.3)
Requires-Dist: s3transfer (==0.6.1)
Requires-Dist: six (==1.16.0)
Requires-Dist: sqlalchemy (==1.4.49)
Requires-Dist: sqlparse (==0.4.4)
Requires-Dist: tomli (==2.0.1)
Requires-Dist: typing-extensions (==4.7.1)
Requires-Dist: urllib3 (==1.26.16)
